af/__init__.py
af/af_dir.py
af/af_dir_worker.py
af/af_file.py
af/encoding_detector.py
af/language_detector.py
af/main.py
af/monitor.py
af/shared_memory.py
af-1.0.2.data/scripts/af2bilingual
af-1.0.2.dist-info/METADATA
af-1.0.2.dist-info/RECORD
af-1.0.2.dist-info/WHEEL
af-1.0.2.dist-info/top_level.txt
