Metadata-Version: 2.1
Name: af
Version: 1.0.2
Summary: Af format tools
Home-page: https://github.com/pypa/example-project
Author: Laurent Bié
Author-email: hloplol@gmail.com
License: UNKNOWN
Platform: UNKNOWN
Classifier: Programming Language :: Python :: 3
Classifier: License :: OSI Approved :: MIT License
Requires-Dist: polyglot
Requires-Dist: six
Requires-Dist: pycld2
Requires-Dist: PyICU
Requires-Dist: PTable
Requires-Dist: markdown
Requires-Dist: tqdm
Requires-Dist: chardet
